textmate/__init__.py
textmate/grammar.py
textmate/grammar.pyi
textmate/rule.py
textmate/rule.pyi
textmate/source.py
textmate/source.pyi
python_textmate-0.2.0.dist-info/LICENSE
python_textmate-0.2.0.dist-info/METADATA
python_textmate-0.2.0.dist-info/WHEEL
python_textmate-0.2.0.dist-info/RECORD
