Metadata-Version: 2.1
Name: python-textmate
Version: 0.2.0
Summary: TextMate grammar parser for python
License: MIT
Author: Marcel Alexandru Nitan
Author-email: nitan.marcel@protonmail.com
Requires-Python: >=3.8,<4.0
Classifier: License :: OSI Approved :: MIT License
Classifier: Programming Language :: Python :: 3
Classifier: Programming Language :: Python :: 3.8
Classifier: Programming Language :: Python :: 3.9
Classifier: Programming Language :: Python :: 3.10
Classifier: Programming Language :: Python :: 3.11
Classifier: Programming Language :: Python :: 3.12
Requires-Dist: onigurumacffi (>=1.3.0,<2.0.0)
